choice_composer/__init__.py
choice_composer/__main__.py
choices/__init__.py
choices/__main__.py
choice_composer-1.0.3.dist-info/LICENSE
choice_composer-1.0.3.dist-info/METADATA
choice_composer-1.0.3.dist-info/WHEEL
choice_composer-1.0.3.dist-info/entry_points.txt
choice_composer-1.0.3.dist-info/top_level.txt
choice_composer-1.0.3.dist-info/RECORD
