Metadata-Version: 2.1
Name: choice-composer
Version: 1.0.3
Summary: It will help you to make choice filed.
Home-page: https://github.com/ImamHossainRoni/choice-composer
Author: Imam Hossain Roni
Author-email: imamhossainroni95@gmail.com
License: MIT
Platform: UNKNOWN
Classifier: License :: OSI Approved :: MIT License
Classifier: Programming Language :: Python :: 3.6
Classifier: Programming Language :: Python :: 3.7
Classifier: Programming Language :: Python :: 3.8
